sunshine_trigger/__init__.py
sunshine_trigger/sunshine_trigger.py
sunshine_trigger-1.0.2.dist-info/licenses/LICENSE
sunshine_trigger-1.0.2.dist-info/METADATA
sunshine_trigger-1.0.2.dist-info/WHEEL
sunshine_trigger-1.0.2.dist-info/top_level.txt
sunshine_trigger-1.0.2.dist-info/RECORD
