Metadata-Version: 2.4
Name: sunshine-trigger
Version: 1.0.2
Summary: Tool for executing commands on sunrise and sunset
Home-page: https://github.com/51CGO/python-sunshine-trigger
Author: Christophe Godart
Author-email: 51CGO@lilo.org
Classifier: Programming Language :: Python :: 3
License-File: LICENSE
Requires-Dist: suntimes
Dynamic: author
Dynamic: author-email
Dynamic: classifier
Dynamic: description
Dynamic: description-content-type
Dynamic: home-page
Dynamic: license-file
Dynamic: requires-dist
Dynamic: summary
